__init__.py
arc_core-0.1.0.dist-info/METADATA
arc_core-0.1.0.dist-info/WHEEL
arc_core-0.1.0.dist-info/entry_points.txt
contants.py
datasets.py
grid.py
pair.py
task.py
utils.py
arc_core-0.1.0.dist-info/RECORD
