Metadata-Version: 2.1
Name: arc-core
Version: 0.1.0
Summary: Core package of ARC-RTK
Author-Email: Jumyung Park <parkjumyungpublic@gmail.com>
Requires-Python: >=3.13
Requires-Dist: numpy>=2.2.4
Requires-Dist: requests>=2.32.3
